<annotation>
	<folder>train5</folder>
	<filename>ngimage108.jpg</filename>
	<path>/home/sankar/Desktop/SankarMTP/stage2/images/train5/ngimage108.jpg</path>
	<source>
		<database>Unknown</database>
	</source>
	<size>
		<width>522</width>
		<height>720</height>
		<depth>3</depth>
	</size>
	<segmented>0</segmented>
	<object>
		<name>NOTSAFE</name>
		<pose>Unspecified</pose>
		<truncated>0</truncated>
		<difficult>0</difficult>
		<bndbox>
			<xmin>198</xmin>
			<ymin>23</ymin>
			<xmax>363</xmax>
			<ymax>387</ymax>
		</bndbox>
	</object>
</annotation>
