<annotation>
	<folder>train5</folder>
	<filename>ngimage261.jpg</filename>
	<path>/home/sankar/Desktop/SankarMTP/stage2/images/train5/ngimage261.jpg</path>
	<source>
		<database>Unknown</database>
	</source>
	<size>
		<width>420</width>
		<height>560</height>
		<depth>3</depth>
	</size>
	<segmented>0</segmented>
	<object>
		<name>NOTSAFE</name>
		<pose>Unspecified</pose>
		<truncated>1</truncated>
		<difficult>0</difficult>
		<bndbox>
			<xmin>78</xmin>
			<ymin>1</ymin>
			<xmax>300</xmax>
			<ymax>509</ymax>
		</bndbox>
	</object>
</annotation>
