<annotation>
	<folder>trainedit</folder>
	<filename>nimage209.jpg</filename>
	<path>/home/sankar/Desktop/SankarMTP/stage2/images/TrainValSet/trainedit/nimage209.jpg</path>
	<source>
		<database>Unknown</database>
	</source>
	<size>
		<width>1920</width>
		<height>1080</height>
		<depth>3</depth>
	</size>
	<segmented>0</segmented>
	<object>
		<name>SAFE</name>
		<pose>Unspecified</pose>
		<truncated>1</truncated>
		<difficult>0</difficult>
		<bndbox>
			<xmin>174</xmin>
			<ymin>47</ymin>
			<xmax>595</xmax>
			<ymax>1080</ymax>
		</bndbox>
	</object>
	<object>
		<name>SAFE</name>
		<pose>Unspecified</pose>
		<truncated>0</truncated>
		<difficult>0</difficult>
		<bndbox>
			<xmin>672</xmin>
			<ymin>288</ymin>
			<xmax>860</xmax>
			<ymax>379</ymax>
		</bndbox>
	</object>
	<object>
		<name>SAFE</name>
		<pose>Unspecified</pose>
		<truncated>0</truncated>
		<difficult>0</difficult>
		<bndbox>
			<xmin>1049</xmin>
			<ymin>58</ymin>
			<xmax>1202</xmax>
			<ymax>384</ymax>
		</bndbox>
	</object>
	<object>
		<name>SAFE</name>
		<pose>Unspecified</pose>
		<truncated>0</truncated>
		<difficult>0</difficult>
		<bndbox>
			<xmin>1351</xmin>
			<ymin>5</ymin>
			<xmax>1763</xmax>
			<ymax>991</ymax>
		</bndbox>
	</object>
	<object>
		<name>SAFE</name>
		<pose>Unspecified</pose>
		<truncated>0</truncated>
		<difficult>0</difficult>
		<bndbox>
			<xmin>1763</xmin>
			<ymin>75</ymin>
			<xmax>1856</xmax>
			<ymax>316</ymax>
		</bndbox>
	</object>
</annotation>
