<annotation>
	<folder>train8</folder>
	<filename>person_without_helmet284.jpg</filename>
	<path>/home/sankar/Desktop/SankarMTP/stage2/images/train8/person_without_helmet284.jpg</path>
	<source>
		<database>Unknown</database>
	</source>
	<size>
		<width>200</width>
		<height>305</height>
		<depth>3</depth>
	</size>
	<segmented>0</segmented>
	<object>
		<name>NOTSAFE</name>
		<pose>Unspecified</pose>
		<truncated>0</truncated>
		<difficult>0</difficult>
		<bndbox>
			<xmin>58</xmin>
			<ymin>112</ymin>
			<xmax>182</xmax>
			<ymax>271</ymax>
		</bndbox>
	</object>
	<object>
		<name>NOTSAFE</name>
		<pose>Unspecified</pose>
		<truncated>0</truncated>
		<difficult>0</difficult>
		<bndbox>
			<xmin>93</xmin>
			<ymin>25</ymin>
			<xmax>177</xmax>
			<ymax>137</ymax>
		</bndbox>
	</object>
</annotation>
