<annotation>
	<folder>train9</folder>
	<filename>worker697.jpg</filename>
	<path>/home/sankar/Desktop/SankarMTP/stage2/images/train9/worker697.jpg</path>
	<source>
		<database>Unknown</database>
	</source>
	<size>
		<width>177</width>
		<height>284</height>
		<depth>3</depth>
	</size>
	<segmented>0</segmented>
	<object>
		<name>SAFE</name>
		<pose>Unspecified</pose>
		<truncated>0</truncated>
		<difficult>0</difficult>
		<bndbox>
			<xmin>108</xmin>
			<ymin>77</ymin>
			<xmax>176</xmax>
			<ymax>257</ymax>
		</bndbox>
	</object>
	<object>
		<name>SAFE</name>
		<pose>Unspecified</pose>
		<truncated>0</truncated>
		<difficult>0</difficult>
		<bndbox>
			<xmin>29</xmin>
			<ymin>91</ymin>
			<xmax>109</xmax>
			<ymax>262</ymax>
		</bndbox>
	</object>
</annotation>
