<annotation>
	<folder>train9</folder>
	<filename>worker851.jpg</filename>
	<path>/home/sankar/Desktop/SankarMTP/stage2/images/train9/worker851.jpg</path>
	<source>
		<database>Unknown</database>
	</source>
	<size>
		<width>344</width>
		<height>146</height>
		<depth>1</depth>
	</size>
	<segmented>0</segmented>
	<object>
		<name>NoJacket</name>
		<pose>Unspecified</pose>
		<truncated>1</truncated>
		<difficult>0</difficult>
		<bndbox>
			<xmin>120</xmin>
			<ymin>2</ymin>
			<xmax>241</xmax>
			<ymax>146</ymax>
		</bndbox>
	</object>
</annotation>
