<annotation>
	<folder>train9</folder>
	<filename>worker646.jpg</filename>
	<path>/home/sankar/Desktop/SankarMTP/stage2/images/train9/worker646.jpg</path>
	<source>
		<database>Unknown</database>
	</source>
	<size>
		<width>273</width>
		<height>184</height>
		<depth>3</depth>
	</size>
	<segmented>0</segmented>
	<object>
		<name>NoJacket</name>
		<pose>Unspecified</pose>
		<truncated>1</truncated>
		<difficult>0</difficult>
		<bndbox>
			<xmin>1</xmin>
			<ymin>5</ymin>
			<xmax>142</xmax>
			<ymax>183</ymax>
		</bndbox>
	</object>
	<object>
		<name>SAFE</name>
		<pose>Unspecified</pose>
		<truncated>1</truncated>
		<difficult>0</difficult>
		<bndbox>
			<xmin>129</xmin>
			<ymin>1</ymin>
			<xmax>258</xmax>
			<ymax>183</ymax>
		</bndbox>
	</object>
</annotation>
